zope/copy/__init__.py
zope/copy/_compat.py
zope/copy/examples.py
zope/copy/interfaces.py
zope/copy/tests/__init__.py
zope/copy/tests/test_copy.py
zope_copy-6.0.dist-info/licenses/LICENSE.txt
zope_copy-6.0.dist-info/METADATA
zope_copy-6.0.dist-info/WHEEL
zope_copy-6.0.dist-info/top_level.txt
zope_copy-6.0.dist-info/RECORD
